piec/__init__.py
piec/_version.py
piec/analysis/__init__.py
piec/analysis/hysteresis.py
piec/analysis/pund.py
piec/analysis/utilities.py
piec/drivers/__init__.py
piec/drivers/digilent.py
piec/drivers/instrument.py
piec/drivers/instrument_old.py
piec/drivers/registry_cache.json
piec/drivers/scpi.py
piec/drivers/utilities.py
piec/drivers/virtual_instrument.py
piec/drivers/awg/__init__.py
piec/drivers/awg/awg.py
piec/drivers/awg/k_81150a.py
piec/drivers/awg/sdg2000.py
piec/drivers/awg/virtual_awg.py
piec/drivers/daq/__init__.py
piec/drivers/daq/daq.py
piec/drivers/daq/mccdig.py
piec/drivers/dmm/__init__.py
piec/drivers/dmm/dmm.py
piec/drivers/lockin/__init__.py
piec/drivers/lockin/lockin.py
piec/drivers/lockin/srs830.py
piec/drivers/lockin/srs830_old.py
piec/drivers/oscilloscope/__init__.py
piec/drivers/oscilloscope/k_dsox3024a.py
piec/drivers/oscilloscope/oscilloscope.py
piec/drivers/oscilloscope/virtual_oscilloscope.py
piec/drivers/pulser/__init__.py
piec/drivers/pulser/pulser.py
piec/drivers/rf_source/__init__.py
piec/drivers/rf_source/rf_source.py
piec/drivers/sourcemeter/__init__.py
piec/drivers/sourcemeter/edc522.py
piec/drivers/sourcemeter/keithley193a.py
piec/drivers/sourcemeter/sourcemeter.py
piec/drivers/stepper_motor/__init__.py
piec/drivers/stepper_motor/arduino_stepper.py
piec/drivers/stepper_motor/stepper_motor.py
piec/drivers/z_old/__init__.py
piec/drivers/z_old/arduino.py
piec/drivers/z_old/instrument.py
piec/drivers/z_old/mccdig.py
piec/drivers/z_old/scpi_instrument.py
piec/drivers/z_old/utilities.py
piec/drivers/z_old/virtual_osc_trace.csv
piec/drivers/z_old/virtual_scpi_queries.json
piec/drivers/z_old/edc522/__init__.py
piec/drivers/z_old/edc522/core.py
piec/drivers/z_old/keithley193a/__init__.py
piec/drivers/z_old/keithley193a/core.py
piec/drivers/z_old/keysight81150a/__init__.py
piec/drivers/z_old/keysight81150a/core.py
piec/drivers/z_old/keysightdsox3024a/__init__.py
piec/drivers/z_old/keysightdsox3024a/core.py
piec-0.1.4.dist-info/licenses/LICENSE
piec-0.1.4.dist-info/METADATA
piec-0.1.4.dist-info/WHEEL
piec-0.1.4.dist-info/top_level.txt
piec-0.1.4.dist-info/RECORD
