Metadata-Version: 2.4
Name: piec
Version: 0.1.4
Summary: A collection of control and analysis code for experiments
Home-page: https://github.com/ElPsyKurisu/piec
Author: Geo Fratian
Author-email: geo_fratian@brown.edu
Project-URL: Bug Tracker, https://github.com/ElPsyKurisu/piec/issues
Project-URL: repository, https://github.com/ElPsyKurisu/piec
Project-URL: Documentation, https://piec.readthedocs.io
Classifier: Programming Language :: Python :: 3
Classifier: License :: OSI Approved :: MIT License
Classifier: Operating System :: OS Independent
Requires-Python: >=3.6
License-File: LICENSE
Requires-Dist: pandas>=1.3.2
Requires-Dist: numpy>=1.19.2
Requires-Dist: matplotlib>=3.3.4
Requires-Dist: scipy>=1.6.2
Requires-Dist: pyvisa>=1.11.3
Requires-Dist: PyVISA-py>=0.7.2
Requires-Dist: IPython>=7.22.0
Requires-Dist: sphinx==7.1.2
Requires-Dist: sphinx-rtd-theme==1.3.0rc1
Requires-Dist: mcculw==1.0.0
Dynamic: license-file
